{
  "get": {
    "operationId": "getBackupConfig",
    "summary": "Get config",
    "description": "Get the configuration of your backups.",
    "tags": [
      "Backups"
    ],
    "security": [
      {
        "bearer_auth": [
          "read"
        ]
      },
      {
        "query_auth": [
          "read"
        ]
      }
    ],
    "responses": {
      "200": {
        "description": "Success",
        "content": {
          "application/json": {
            "schema": {
              "$ref": "../components/schemas/config.json"
            }
          }
        }
      },
      "401": {
        "$ref": "../components/responses/unauthorized.json"
      },
      "403": {
        "$ref": "../components/responses/forbidden.json"
      },
      "500": {
        "$ref": "../components/responses/server_error.json"
      }
    },
    "x-codeSamples": [
      {
        "lang": "cURL",
        "source": {
          "$ref": "../code_samples/cURL/backups_config/get.sh"
        }
      }
    ]
  }
}